{
    "code": 0,
    "msg": null,
    "url": null,
    "data": {
        "totalSize": 70,
        "totalPageCount": 4,
        "pageIndex": 1,
        "pageSize": 20,
        "list": [{
            "id": "0f8f3877-c920-4be4-a3e7-109d15e20bad",
            "text": "黄色的花遍地摇曳，紫色的花漫山遍野，红色的花随着山岗连绵起伏，流水一样的人生，静静看花开花落。",
            "collectFlag": false
        }, {
            "id": "1186fa72-fb37-429d-a990-08b719e70bd8",
            "text": "你可曾知道，我总是在下雨时分，宁静与忧伤之间，最想念你。你可曾知道，我总是在落雪时节，沉默与孤独之间，最想念你。",
            "collectFlag": false
        }, {
            "id": "11e9003d-cc18-4f8c-96b5-3b2c2a5f516f",
            "text": "因为偶然，蔷薇岛屿上长着两棵樱桃树。因为偶然，茫茫人海中多了两个相爱的人。一个人是一座蔷薇岛屿。",
            "collectFlag": false
        }, {
            "id": "1257582d-6dfa-4154-9915-864123f818b2",
            "text": "离开一个人，才知道自己有多么的需要他。",
            "collectFlag": false
        }, {
            "id": "165b646d-8e19-4ca5-8657-8e34fba426f3",
            "text": "他们是邻居，隔着一道矮墙。她喊他泥娃哥，他喊她幺妹。",
            "collectFlag": false
        }, {
            "id": "1d18ab19-3b9c-4000-be57-50ea31491006",
            "text": "我走过你曾走过的街头，徘徊在你徘徊过的路口。",
            "collectFlag": false
        }, {
            "id": "1f0eb5e1-392f-4226-a5af-1cbbf069a853",
            "text": "一个少年眼神中流露的叛逆和颓废并不是伪装的",
            "collectFlag": false
        }, {
            "id": "219e510a-0353-483f-87d5-4d819b98fd9b",
            "text": "我可以给你一百朵关于蔷薇的回忆 却没有勇气献给你一束玫瑰。",
            "collectFlag": false
        }, {
            "id": "21a362e6-ccff-467d-93aa-a02ca7ab38c9",
            "text": "每个人都是如此，左手属于恶魔，右手属于天使。",
            "collectFlag": false
        }, {
            "id": "22e5d92f-ab7a-4adf-a0fa-e1d4b3a0bbe0",
            "text": "月下临风一刀斩，云意沉沉红花畔。烂柯亭前醉赊酒，腰束贼头上梁山！",
            "collectFlag": false
        }, {
            "id": "253f3555-5816-4f24-aa58-cd8a79c478a9",
            "text": "儿童乞丐是城市里畸形的怪物，这怪物的父亲叫做冷漠，母亲的名字叫做视而不见！",
            "collectFlag": false
        }, {
            "id": "29e4aa40-6a24-44c0-980c-2bb3dbbdab80",
            "text": "人对痛苦和折磨，有着极强的忍耐力。",
            "collectFlag": false
        }, {
            "id": "29e80c37-a4e6-45b8-b856-63c945561519",
            "text": "雨，不可拆解，只能由两部分组成：水和思念。",
            "collectFlag": false
        }, {
            "id": "2bfe4bcd-b10f-4528-bef9-06caf072e460",
            "text": "梅花落在地上，和白雪一起吹散，漂流瓶不再漂流，半个身子嵌入冰中。",
            "collectFlag": false
        }, {
            "id": "330d7371-d0b2-4f75-a0bc-cb796e6b7c8e",
            "text": "红旗飘扬在学校上空，两个年轻少年在国歌声中离开了校园，他们迎着冷眼与嘲笑，踏上茫茫未知的旅途，向着远方，身影渐行渐远……",
            "collectFlag": false
        }, {
            "id": "34123031-1cc1-4194-a94b-0eb49f153e65",
            "text": "其实任何一个我们身边看似普通的人，都存在他背后所不为人知晓的另一面。",
            "collectFlag": false
        }, {
            "id": "34490ff8-fd84-4927-b322-d4ddad0235fa",
            "text": "我们的往事中总有那么一个雨天，那天下起了一生一世中最大的一场雨，永难忘怀。",
            "collectFlag": false
        }, {
            "id": "38ef532c-98d7-41b3-a53a-d438706fceff",
            "text": "一只手握住另一只手，需要穿透多少乌云，需要多么大的勇气？他乡有人吹箫，他乡菊花泛黄。",
            "collectFlag": false
        }, {
            "id": "3daa247e-4c11-4ffd-bebf-d7b3b31d0c2f",
            "text": "河堤是两个很陡的雪坡，他先上去，蹲在上面向她伸出手，男孩的脸上带着纯净的微笑，如同雪后初晴的阳光，如同冰雪消融后的春风，温暖从一只手传递给另一只手，最终抵达心脏。他们的初恋，第一次也是最后一次。",
            "collectFlag": false
        }, {
            "id": "40d296b3-c5ab-4f37-bc8d-fcff42a33262",
            "text": "研究一场爱情的发生简直和探究宇宙的起源同样困难，她们是如何相爱的呢。",
            "collectFlag": false
        }]
    }
}
